openxr/__init__.py
openxr/abi.py
openxr/action.py
openxr/action_set.py
openxr/api.py
openxr/extension.py
openxr/handle.py
openxr/instance.py
openxr/layer.py
openxr/result.py
openxr/session.py
openxr/space.py
openxr/swapchain.py
openxr/system.py
openxr-0.0.5.dist-info/METADATA
openxr-0.0.5.dist-info/UNLICENSE
openxr-0.0.5.dist-info/WHEEL
openxr-0.0.5.dist-info/top_level.txt
openxr-0.0.5.dist-info/RECORD
