Metadata-Version: 2.1
Name: openxr
Version: 0.0.5
Summary: OpenXR bindings for Python.
Home-page: https://github.com/drypy/openxr.py
Author: Arto Bendiken
Author-email: arto@bendiken.net
License: Public Domain
Project-URL: Bug Tracker, https://github.com/drypy/openxr.py/issues
Project-URL: Documentation, https://github.com/drypy/openxr.py/blob/master/README.md
Project-URL: Source Code, https://github.com/drypy/openxr.py
Platform: UNKNOWN
Classifier: Development Status :: 2 - Pre-Alpha
Classifier: Environment :: Console
Classifier: Intended Audience :: Developers
Classifier: Intended Audience :: Information Technology
Classifier: License :: Public Domain
Classifier: Natural Language :: English
Classifier: Operating System :: OS Independent
Classifier: Programming Language :: Python :: 3 :: Only
Classifier: Programming Language :: Python :: 3.6
Classifier: Programming Language :: Python :: 3.7
Classifier: Programming Language :: Python :: 3.8
Classifier: Programming Language :: Python :: 3.9
Classifier: Topic :: Multimedia :: Graphics :: 3D Rendering
Classifier: Topic :: Scientific/Engineering :: Human Machine Interfaces
Classifier: Topic :: Software Development :: User Interfaces
Requires-Python: ~=3.6
Requires-Dist: dogma.py (>=0)
Provides-Extra: test
Requires-Dist: pytest ; extra == 'test'
